<annotation>
	<folder>wheat</folder>
	<filename>c7.png</filename>
	<path>/Users/emericbayard/Dropbox/Projet/minobot/assets/wheat/c7.png</path>
	<source>
		<database>Unknown</database>
	</source>
	<size>
		<width>2248</width>
		<height>1536</height>
		<depth>3</depth>
	</size>
	<segmented>0</segmented>
	<object>
		<name>wheat</name>
		<pose>Unspecified</pose>
		<truncated>0</truncated>
		<difficult>0</difficult>
		<bndbox>
			<xmin>58</xmin>
			<ymin>886</ymin>
			<xmax>243</xmax>
			<ymax>1028</ymax>
		</bndbox>
	</object>
	<object>
		<name>wheat</name>
		<pose>Unspecified</pose>
		<truncated>0</truncated>
		<difficult>0</difficult>
		<bndbox>
			<xmin>138</xmin>
			<ymin>1310</ymin>
			<xmax>319</xmax>
			<ymax>1454</ymax>
		</bndbox>
	</object>
	<object>
		<name>wheat</name>
		<pose>Unspecified</pose>
		<truncated>1</truncated>
		<difficult>0</difficult>
		<bndbox>
			<xmin>138</xmin>
			<ymin>1391</ymin>
			<xmax>312</xmax>
			<ymax>1536</ymax>
		</bndbox>
	</object>
	<object>
		<name>wheat</name>
		<pose>Unspecified</pose>
		<truncated>0</truncated>
		<difficult>0</difficult>
		<bndbox>
			<xmin>1460</xmin>
			<ymin>649</ymin>
			<xmax>1623</xmax>
			<ymax>793</ymax>
		</bndbox>
	</object>
	<object>
		<name>wheat</name>
		<pose>Unspecified</pose>
		<truncated>0</truncated>
		<difficult>0</difficult>
		<bndbox>
			<xmin>1460</xmin>
			<ymin>734</ymin>
			<xmax>1649</xmax>
			<ymax>889</ymax>
		</bndbox>
	</object>
</annotation>
